pypatronus-0.34.2.dist-info/METADATA
pypatronus-0.34.2.dist-info/WHEEL
pypatronus/__init__.py
pypatronus/pypatronus.cpython-314-darwin.so
pypatronus-0.34.2.dist-info/RECORD
