Metadata-Version: 2.4
Name: pypatronus
Version: 0.34.2
Classifier: Programming Language :: Rust
Classifier: Programming Language :: Python
Classifier: License :: OSI Approved :: BSD License
Summary: The hardware bug-finding toolkit for Python programmers.
Author-email: Adwait Godbole <adwait@berkeley.edu>, Kevin Laeufer <laeufer@cornell.edu>
License-Expression: BSD-3-Clause
Requires-Python: >=3.9
Project-URL: Homepage, https://github.com/cucapra/patronus
Project-URL: Issues, https://github.com/cucapra/patronus/issues
